jefferson_street_composer/__init__.py
jefferson_street_composer/services/__init__.py
jefferson_street_composer/services/specifications/__init__.py
jefferson_street_composer/services/specifications/base_dbt_dag.py
jefferson_street_composer/services/specifications/base_ingest_dag.py
jefferson_street_composer-1.7.1.dist-info/METADATA
jefferson_street_composer-1.7.1.dist-info/WHEEL
jefferson_street_composer-1.7.1.dist-info/RECORD
