Metadata-Version: 2.1
Name: jefferson-street-composer
Version: 1.7.1
Summary: Library for Jefferson Street Technologies Composer Configuration
Author: Nikolai McFall
Author-email: nikolai@jeffersonst.io
Requires-Python: >=3.8,<3.9
Classifier: Programming Language :: Python :: 3
Classifier: Programming Language :: Python :: 3.8
Requires-Dist: apache-airflow (==2.7.1)
Requires-Dist: apache-airflow-providers-cncf-kubernetes (>=7.14.0,<8.0.0)
